{
  "_id": "bitcoin-sv@bitcoin-sv",
  "asset": "bitcoin-sv",
  "platform": "bitcoin-sv",
  "type": "coin",
  "name": "Bitcoin SV",
  "symbol": "BSV",
  "decimals": 8,
  "logo": "bitcoin-sv.svg",
  "scheme": "bitcoinsv",
  "supported": false,
  "changelly": {
    "ticker": "bsv"
  },
  "changenow": {
    "ticker": "bsv",
    "network": "bsv"
  },
  "coingecko": {
    "id": "bitcoin-cash-sv"
  },
  "coinmarketcap": {
    "id": 3602,
    "slug": "bitcoin-sv"
  },
  "guardarian": {
    "ticker": "BSV",
    "network": "BSV"
  }
}