{
  "_id": "dash@dash",
  "asset": "dash",
  "platform": "dash",
  "type": "coin",
  "name": "Dash",
  "symbol": "DASH",
  "decimals": 8,
  "logo": "dash.svg",
  "scheme": "dash",
  "bitnovo": {
    "id": "DASH"
  },
  "changelly": {
    "ticker": "dash"
  },
  "changenow": {
    "ticker": "dash",
    "network": "dash"
  },
  "coingecko": {
    "id": "dash"
  },
  "coinmarketcap": {
    "id": 131,
    "slug": "dash"
  },
  "guardarian": {
    "ticker": "DASH",
    "network": "DASH"
  },
  "moonpay": {
    "id": "fdc552b0-e45c-4295-afc1-2ff12272e303",
    "code": "dash_dash"
  },
  "onramper": {
    "id": "DASH_DASH"
  },
  "paybis": {
    "id": "DASH"
  }
}