{
  "_id": "venus@binance-smart-chain",
  "asset": "venus",
  "platform": "binance-smart-chain",
  "type": "token",
  "name": "Venus",
  "symbol": "XVS",
  "address": "0xcf6bb5389c92bdda8a3747ddb454cb7a64626c63",
  "decimals": 18,
  "logo": "venus.png",
  "changelly": {
    "ticker": "xvs"
  },
  "changenow": {
    "ticker": "xvs",
    "network": "bsc"
  },
  "coingecko": {
    "id": "venus",
    "platform": "binance-smart-chain"
  },
  "coinmarketcap": {
    "id": 7288,
    "slug": "venus"
  }
}